instagram_private_api/__init__.py
instagram_private_api/client.py
instagram_private_api/compat.py
instagram_private_api/compatpatch.py
instagram_private_api/constants.py
instagram_private_api/errors.py
instagram_private_api/http.py
instagram_private_api/utils.py
instagram_private_api/endpoints/__init__.py
instagram_private_api/endpoints/accounts.py
instagram_private_api/endpoints/collections.py
instagram_private_api/endpoints/common.py
instagram_private_api/endpoints/discover.py
instagram_private_api/endpoints/feed.py
instagram_private_api/endpoints/friendships.py
instagram_private_api/endpoints/highlights.py
instagram_private_api/endpoints/igtv.py
instagram_private_api/endpoints/live.py
instagram_private_api/endpoints/locations.py
instagram_private_api/endpoints/media.py
instagram_private_api/endpoints/misc.py
instagram_private_api/endpoints/tags.py
instagram_private_api/endpoints/upload.py
instagram_private_api/endpoints/users.py
instagram_private_api/endpoints/usertags.py
instagram_web_api/__init__.py
instagram_web_api/client.py
instagram_web_api/common.py
instagram_web_api/compat.py
instagram_web_api/compatpatch.py
instagram_web_api/errors.py
instagram_web_api/http.py
instagram_private_api-1.6.0.0.dist-info/LICENSE
instagram_private_api-1.6.0.0.dist-info/METADATA
instagram_private_api-1.6.0.0.dist-info/WHEEL
instagram_private_api-1.6.0.0.dist-info/top_level.txt
instagram_private_api-1.6.0.0.dist-info/RECORD
