Metadata-Version: 2.1
Name: instagram-private-api
Version: 1.6.0.0
Summary: A client interface for the private Instagram API.
Home-page: https://github.com/ping/instagram_private_api/tree/master
Author: ping
Author-email: lastmodified@gmail.com
License: MIT
Keywords: instagram private api
Platform: UNKNOWN
Classifier: Development Status :: 4 - Beta
Classifier: Intended Audience :: Developers
Classifier: License :: OSI Approved :: MIT License
Classifier: Topic :: Software Development :: Libraries :: Python Modules
Classifier: Programming Language :: Python :: 2.7
Classifier: Programming Language :: Python :: 3.5
